{
  "status": 200,
  "message": "Success",
  "videos": [
    {
      "videoid": 4592,
      "videokey": "W8YY16SSAAXO",
      "video_password": null,
      "video_users": "",
      "username": "",
      "userid": 1,
      "partner_id": null,
      "maturity_level": "all",
      "title": "Avatar: The Way of Water",
      "file_name": "1680240135kTfgJMQlTp",
      "file_type": 2,
      "description": "Set more than a decade after the events of the first film, learn the story of the Sully family (Jake, Neytiri, and their kids), the trouble that follows them, the lengths they go to keep each other safe, the battles they fight to stay alive, and the tragedies they endure.",
      "tags": "loss of loved one,dying and death,alien life-form,resurrection,sequel,dysfunctional family,alien planet,distant future,adopted child,rebirth,family dynamics,adopted son,stronger villain,war",
      "category": "#1# #11# #23# #37# ",
      "category_parents": "",
      "broadcast": "public",
      "location": "0",
      "datecreated": "2023-03-31",
      "country": "0",
      "blocked_countries": "#0# ",
      "allowed_countries": "0",
      "sprite_count": 0,
      "season_id": 0,
      "series_id": 0,
      "sequence": 0,
      "allow_embedding": "",
      "rating": 0,
      "rated_by": "0",
      "voter_ids": "",
      "featured": "no",
      "featured_order": null,
      "featured_date": "0000-00-00 00:00:00",
      "featured_description": "",
      "allow_rating": "yes",
      "allow_comments": "yes",
      "comments_count": 0,
      "last_commented": null,
      "active": "yes",
      "favourite_count": "0",
      "playlist_count": "0",
      "views": 45,
      "last_viewed": "0000-00-00 00:00:00",
      "date_added": "2023-03-31",
      "flagged": "no",
      "duration": "3h 12m",
      "status": "Successful",
      "failed_reason": "none",
      "default_thumb": 211999,
      "aspect_ratio": "",
      "embed_code": "",
      "refer_url": "",
      "downloads": 0,
      "uploader_ip": "110.93.203.74",
      "mass_embed_status": "no",
      "unique_embed_code": "",
      "remote_play_url": "",
      "video_files": "[360,480,720,240,1080]",
      "server_ip": "",
      "file_server_path": "",
      "file_directory": "2023/03/31",
      "files_thumbs_path": "",
      "file_thumbs_count": "",
      "has_hq": "no",
      "filegrp_size": "",
      "process_status": 4,
      "video_version": "2.8",
      "extras": "",
      "subscription_email": "pending",
      "thumbs_version": "3.0",
      "re_conv_status": "",
      "conv_progress": "",
      "is_premium": "no",
      "override_default_monetization": 0,
      "credits_required": null,
      "rental_hours": 0,
      "premium_cid": 0,
      "in_editor_pick": "no",
      "has_subs": "no",
      "total_subs": 0,
      "last_sub_num": 0,
      "live": "",
      "udp_live": null,
      "force_hls_http_url": null,
      "start_published_date": "2023-03-31 11:32:30",
      "end_published_date": null,
      "has_sprite": "no",
      "version": 1,
      "has_resulotion": "no",
      "aws_service_id": 0,
      "aws_cdn": "",
      "aws_thumb_path": "",
      "license_by": "",
      "is_channeHome": "no",
      "super_feature": 0,
      "is_avod": 1,
      "is_tvod": 0,
      "pre_order": 0,
      "live_status": 0,
      "deleted_at": null,
      "content_type": 1,
      "is_360": 0,
      "projection_type": "NONE",
      "epg_channel_id": "",
      "drm_protected": "no",
      "epg_url": null,
      "content_language": null,
      "dvr_url": null,
      "dvr_backup_timezone": null,
      "dvr_backup_duration": "0",
      "epg_dvr_catchup_url": null,
      "mpaa_rating": null,
      "content_rating_tags": null,
      "logo": "https://vcz-tesvideo-cloud-vodlix-com.b-cdn.net/u/tesvideo/files/video_logos/2023/03/31/1680240135kTfgJMQlTp.png",
      "portrait_thumbs": {
        "original": "https://vcz-tesvideo-cloud-vodlix-com.b-cdn.net/u/tesvideo/files/thumbs/2023/03/31/1680240135kTfgJMQlTp-original-portrait.jpg",
        "160x240": "https://vcz-tesvideo-cloud-vodlix-com.b-cdn.net/u/tesvideo/files/thumbs/2023/03/31/1680240135kTfgJMQlTp-160x240-portrait.jpg",
        "240x360": "https://vcz-tesvideo-cloud-vodlix-com.b-cdn.net/u/tesvideo/files/thumbs/2023/03/31/1680240135kTfgJMQlTp-240x360-portrait.jpg",
        "320x480": "https://vcz-tesvideo-cloud-vodlix-com.b-cdn.net/u/tesvideo/files/thumbs/2023/03/31/1680240135kTfgJMQlTp-320x480-portrait.jpg",
        "480x720": "https://vcz-tesvideo-cloud-vodlix-com.b-cdn.net/u/tesvideo/files/thumbs/2023/03/31/1680240135kTfgJMQlTp-480x720-portrait.jpg",
        "720x1080": "https://vcz-tesvideo-cloud-vodlix-com.b-cdn.net/u/tesvideo/files/thumbs/2023/03/31/1680240135kTfgJMQlTp-720x1080-portrait.jpg"
      },
      "thumbs": {
        "original": "https://vcz-tesvideo-cloud-vodlix-com.b-cdn.net/u/tesvideo/files/thumbs/2023/03/31/1680240135kTfgJMQlTp-original-3.jpg",
        "168x105": "https://vcz-tesvideo-cloud-vodlix-com.b-cdn.net/u/tesvideo/files/thumbs/2023/03/31/1680240135kTfgJMQlTp-168x105-3.jpg",
        "416x260": "https://vcz-tesvideo-cloud-vodlix-com.b-cdn.net/u/tesvideo/files/thumbs/2023/03/31/1680240135kTfgJMQlTp-416x260-3.jpg",
        "632x395": "https://vcz-tesvideo-cloud-vodlix-com.b-cdn.net/u/tesvideo/files/thumbs/2023/03/31/1680240135kTfgJMQlTp-632x395-3.jpg",
        "768x432": "https://vcz-tesvideo-cloud-vodlix-com.b-cdn.net/u/tesvideo/files/thumbs/2023/03/31/1680240135kTfgJMQlTp-768x432-3.jpg",
        "1280x720": "https://vcz-tesvideo-cloud-vodlix-com.b-cdn.net/u/tesvideo/files/thumbs/2023/03/31/1680240135kTfgJMQlTp-1280x720-3.jpg",
        "1920x1080": "https://vcz-tesvideo-cloud-vodlix-com.b-cdn.net/u/tesvideo/files/thumbs/2023/03/31/1680240135kTfgJMQlTp-1920x1080-3.jpg",
        "200x288": "https://vcz-tesvideo-cloud-vodlix-com.b-cdn.net/u/tesvideo/files/thumbs/2023/03/31/1680240135kTfgJMQlTp-200x288-3.jpg"
      },
      "gif": "https://vz-f9ab63d6-07e.b-cdn.net/d3fe9787-75f3-4811-88aa-746c19aa021e/preview.webp",
      "files": [
        "https://tesvideo.cloud.vodlix.com/u/tesvideo/files/videos/no_video.mp4"
      ],
      "watch_url": "/watch/4592",
      "year": "2023",
      "duration_in_seconds": "11575",
      "rate": 0,
      "trailers": null,
      "fav_id": null,
      "is_fav": null,
      "url": "/watch/4592",
      "shareable": "https://trutv.transworld-home.com/watch/4592",
      "copy_url": "https://tesvideo.cloud.vodlix.com/movies/title/4592",
      "categories": [
        {
          "category_id": 1,
          "parent_id": 0,
          "category_name": "Action",
          "category_order": 1,
          "category_desc": "",
          "date_added": "2022-11-03 11:52:15",
          "category_thumb": "",
          "featured": "yes",
          "isdefault": "no",
          "navbar": "no",
          "is_trailer": 0,
          "meta_title": null,
          "meta_description": null,
          "meta_keywords": null,
          "is_video": 1,
          "is_series": 0,
          "is_live": 0
        },
        {
          "category_id": 11,
          "parent_id": 0,
          "category_name": "Adventure",
          "category_order": 7,
          "category_desc": "",
          "date_added": "2022-11-11 16:32:09",
          "category_thumb": "",
          "featured": "yes",
          "isdefault": "no",
          "navbar": "no",
          "is_trailer": 0,
          "meta_title": null,
          "meta_description": null,
          "meta_keywords": null,
          "is_video": 1,
          "is_series": 0,
          "is_live": 0
        },
        {
          "category_id": 23,
          "parent_id": 0,
          "category_name": "ALL Movies",
          "category_order": 5,
          "category_desc": "",
          "date_added": "2022-12-12 12:51:18",
          "category_thumb": "",
          "featured": "yes",
          "isdefault": "no",
          "navbar": "no",
          "is_trailer": 0,
          "meta_title": null,
          "meta_description": null,
          "meta_keywords": null,
          "is_video": 1,
          "is_series": 0,
          "is_live": 0
        },
        {
          "category_id": 37,
          "parent_id": 0,
          "category_name": "Sci-Fi",
          "category_order": 31,
          "category_desc": "Sci-Fi",
          "date_added": "2022-12-19 11:33:13",
          "category_thumb": "",
          "featured": "no",
          "isdefault": "no",
          "navbar": "no",
          "is_trailer": 0,
          "meta_title": "Sci-Fi",
          "meta_description": "Sci-Fi",
          "meta_keywords": "Sci-Fi",
          "is_video": 1,
          "is_series": 0,
          "is_live": 0
        }
      ],
      "quality": {
        "hd": "no",
        "uhd": "no"
      },
      "square_thumbs": [
        
      ],
      "interval": "3h 12m",
      "price_tag": null,
      "show_premium_badge": false,
      "can_pre_order": false,
      "availability_date": null,
      "content_type_label": "movie"
    },
    {
      "videoid": 4515,
      "videokey": "H1AX2OAXN1RO",
      "video_password": null,
      "video_users": "",
      "username": "",
      "userid": 1,
      "partner_id": null,
      "maturity_level": "all",
      "title": "ARY-QTV",
      "file_name": "1680161937kZs5mqIE32",
      "file_type": 2,
      "description": "ARY-QTV",
      "tags": "unknown",
      "category": "#3# ",
      "category_parents": "",
      "broadcast": "public",
      "location": "0",
      "datecreated": "2023-03-30",
      "country": "0",
      "blocked_countries": "#0# ",
      "allowed_countries": "0",
      "sprite_count": 0,
      "season_id": 0,
      "series_id": 0,
      "sequence": 342,
      "allow_embedding": "",
      "rating": 0,
      "rated_by": "0",
      "voter_ids": "",
      "featured": "no",
      "featured_order": null,
      "featured_date": "0000-00-00 00:00:00",
      "featured_description": "",
      "allow_rating": "yes",
      "allow_comments": "yes",
      "comments_count": 0,
      "last_commented": null,
      "active": "yes",
      "favourite_count": "0",
      "playlist_count": "0",
      "views": 0,
      "last_viewed": "0000-00-00 00:00:00",
      "date_added": "2023-03-30",
      "flagged": "no",
      "duration": " 0s",
      "status": "Successful",
      "failed_reason": "none",
      "default_thumb": 209003,
      "aspect_ratio": "",
      "embed_code": "",
      "refer_url": "",
      "downloads": 0,
      "uploader_ip": "110.93.192.18",
      "mass_embed_status": "no",
      "unique_embed_code": "",
      "remote_play_url": "",
      "video_files": "",
      "server_ip": "",
      "file_server_path": "",
      "file_directory": "2023/03/30",
      "files_thumbs_path": "",
      "file_thumbs_count": "",
      "has_hq": "no",
      "filegrp_size": "",
      "process_status": 0,
      "video_version": "2.7",
      "extras": "",
      "subscription_email": "pending",
      "thumbs_version": "3.0",
      "re_conv_status": "",
      "conv_progress": "",
      "is_premium": "no",
      "override_default_monetization": 0,
      "credits_required": null,
      "rental_hours": 0,
      "premium_cid": 0,
      "in_editor_pick": "no",
      "has_subs": "no",
      "total_subs": 0,
      "last_sub_num": 0,
      "live": "https://tes.ottervideo.ca/ARY-QTV/video.m3u8",
      "udp_live": "",
      "force_hls_http_url": "https://tes.ottervideo.ca/ARY-QTV/video.m3u8",
      "start_published_date": null,
      "end_published_date": null,
      "has_sprite": "no",
      "version": 1,
      "has_resulotion": "no",
      "aws_service_id": 0,
      "aws_cdn": "",
      "aws_thumb_path": "",
      "license_by": "",
      "is_channeHome": "no",
      "super_feature": 0,
      "is_avod": 1,
      "is_tvod": 0,
      "pre_order": 0,
      "live_status": 0,
      "deleted_at": null,
      "content_type": 4,
      "is_360": 0,
      "projection_type": "NONE",
      "epg_channel_id": "",
      "drm_protected": "no",
      "epg_url": "",
      "content_language": null,
      "dvr_url": "",
      "dvr_backup_timezone": "",
      "dvr_backup_duration": "0",
      "epg_dvr_catchup_url": "",
      "mpaa_rating": null,
      "content_rating_tags": null,
      "logo": "https://vcz-tesvideo-cloud-vodlix-com.b-cdn.net/u/tesvideo/files/video_logos/2023/03/30/1680161937kZs5mqIE32.png",
      "portrait_thumbs": {
        "original": "https://vcz-tesvideo-cloud-vodlix-com.b-cdn.net/u/tesvideo/files/thumbs/2023/03/30/1680161937kZs5mqIE32-original-portrait.jpg",
        "160x240": "https://vcz-tesvideo-cloud-vodlix-com.b-cdn.net/u/tesvideo/files/thumbs/2023/03/30/1680161937kZs5mqIE32-160x240-portrait.jpg",
        "240x360": "https://vcz-tesvideo-cloud-vodlix-com.b-cdn.net/u/tesvideo/files/thumbs/2023/03/30/1680161937kZs5mqIE32-240x360-portrait.jpg",
        "320x480": "https://vcz-tesvideo-cloud-vodlix-com.b-cdn.net/u/tesvideo/files/thumbs/2023/03/30/1680161937kZs5mqIE32-320x480-portrait.jpg",
        "480x720": "https://vcz-tesvideo-cloud-vodlix-com.b-cdn.net/u/tesvideo/files/thumbs/2023/03/30/1680161937kZs5mqIE32-480x720-portrait.jpg",
        "720x1080": "https://vcz-tesvideo-cloud-vodlix-com.b-cdn.net/u/tesvideo/files/thumbs/2023/03/30/1680161937kZs5mqIE32-720x1080-portrait.jpg"
      },
      "thumbs": {
        "original": "https://vcz-tesvideo-cloud-vodlix-com.b-cdn.net/u/tesvideo/files/thumbs/2023/03/30/1680161937kZs5mqIE32-original-HUvRhbJZ.jpg",
        "168x105": "https://vcz-tesvideo-cloud-vodlix-com.b-cdn.net/u/tesvideo/files/thumbs/2023/03/30/1680161937kZs5mqIE32-168x105-HUvRhbJZ.jpg",
        "416x260": "https://vcz-tesvideo-cloud-vodlix-com.b-cdn.net/u/tesvideo/files/thumbs/2023/03/30/1680161937kZs5mqIE32-416x260-HUvRhbJZ.jpg",
        "632x395": "https://vcz-tesvideo-cloud-vodlix-com.b-cdn.net/u/tesvideo/files/thumbs/2023/03/30/1680161937kZs5mqIE32-632x395-HUvRhbJZ.jpg",
        "768x432": "https://vcz-tesvideo-cloud-vodlix-com.b-cdn.net/u/tesvideo/files/thumbs/2023/03/30/1680161937kZs5mqIE32-768x432-HUvRhbJZ.jpg",
        "1280x720": "https://vcz-tesvideo-cloud-vodlix-com.b-cdn.net/u/tesvideo/files/thumbs/2023/03/30/1680161937kZs5mqIE32-1280x720-HUvRhbJZ.jpg",
        "1920x1080": "https://vcz-tesvideo-cloud-vodlix-com.b-cdn.net/u/tesvideo/files/thumbs/2023/03/30/1680161937kZs5mqIE32-1920x1080-HUvRhbJZ.jpg",
        "200x288": "https://vcz-tesvideo-cloud-vodlix-com.b-cdn.net/u/tesvideo/files/thumbs/2023/03/30/1680161937kZs5mqIE32-200x288-HUvRhbJZ.jpg"
      },
      "gif": null,
      "files": [
        "https://tes.ottervideo.ca/ARY-QTV/video.m3u8"
      ],
      "watch_url": "/watch/4515",
      "initials": "<?xml version=\"1.0\" encoding=\"utf-8\"?><svg width=\"48\" height=\"48\" xmlns=\"http://www.w3.org/2000/svg\" xmlns:xlink=\"http://www.w3.org/1999/xlink\"><circle cx=\"24\" cy=\"24\" r=\"24\" style=\"fill: none\" /><text x=\"50%\" y=\"50%\" dy=\".1em\" fill=\"#8b5d5d\" font-size=\"24\" text-anchor=\"middle\" dominant-baseline=\"middle\" style=\"font-family: OpenSans, sans-serif; line-height: 1\">AQ</text></svg>",
      "year": "2023",
      "duration_in_seconds": "0",
      "rate": 0,
      "trailers": null,
      "fav_id": null,
      "is_fav": null,
      "url": "/watch/4515",
      "shareable": "https://trutv.transworld-home.com/watch/4515",
      "copy_url": "https://tesvideo.cloud.vodlix.com/movies/title/4515",
      "categories": [
        {
          "category_id": 3,
          "parent_id": 0,
          "category_name": "Religious",
          "category_order": 48,
          "category_desc": "Religious",
          "date_added": "2022-11-07 05:19:41",
          "category_thumb": "",
          "featured": "no",
          "isdefault": "no",
          "navbar": "no",
          "is_trailer": 0,
          "meta_title": null,
          "meta_description": null,
          "meta_keywords": "Religious",
          "is_video": 0,
          "is_series": 0,
          "is_live": 1
        }
      ],
      "channel_number": 342,
      "max_resolution": "1080p",
      "square_thumbs": {
        "original": "https://vcz-tesvideo-cloud-vodlix-com.b-cdn.net/u/tesvideo/files/thumbs/2023/03/30/1680161937kZs5mqIE32-original-square.jpg",
        "300x300": "https://vcz-tesvideo-cloud-vodlix-com.b-cdn.net/u/tesvideo/files/thumbs/2023/03/30/1680161937kZs5mqIE32-300x300-square.jpg",
        "512x512": "https://vcz-tesvideo-cloud-vodlix-com.b-cdn.net/u/tesvideo/files/thumbs/2023/03/30/1680161937kZs5mqIE32-512x512-square.jpg",
        "1024x1024": "https://vcz-tesvideo-cloud-vodlix-com.b-cdn.net/u/tesvideo/files/thumbs/2023/03/30/1680161937kZs5mqIE32-1024x1024-square.jpg"
      },
      "interval": " 0s",
      "price_tag": null,
      "show_premium_badge": false,
      "can_pre_order": false,
      "availability_date": null,
      "content_type_label": "live"
    },
    {
      "videoid": 4514,
      "videokey": "K9XH39AG2383",
      "video_password": null,
      "video_users": "",
      "username": "",
      "userid": 1,
      "partner_id": null,
      "maturity_level": "all",
      "title": "BBC Lifestyle",
      "file_name": "1680161283OFlIZvF29a",
      "file_type": 2,
      "description": "BBC Lifestyle",
      "tags": "unknown",
      "category": "#17# ",
      "category_parents": "",
      "broadcast": "public",
      "location": "0",
      "datecreated": "2023-03-30",
      "country": "0",
      "blocked_countries": "",
      "allowed_countries": "0",
      "sprite_count": 0,
      "season_id": 0,
      "series_id": 0,
      "sequence": 312,
      "allow_embedding": "",
      "rating": 0,
      "rated_by": "0",
      "voter_ids": "",
      "featured": "no",
      "featured_order": null,
      "featured_date": "0000-00-00 00:00:00",
      "featured_description": "",
      "allow_rating": "yes",
      "allow_comments": "yes",
      "comments_count": 0,
      "last_commented": null,
      "active": "yes",
      "favourite_count": "0",
      "playlist_count": "0",
      "views": 0,
      "last_viewed": "0000-00-00 00:00:00",
      "date_added": "2023-03-30",
      "flagged": "no",
      "duration": " 0s",
      "status": "Successful",
      "failed_reason": "none",
      "default_thumb": 208984,
      "aspect_ratio": "",
      "embed_code": "",
      "refer_url": "",
      "downloads": 0,
      "uploader_ip": "110.93.192.18",
      "mass_embed_status": "no",
      "unique_embed_code": "",
      "remote_play_url": "",
      "video_files": "",
      "server_ip": "",
      "file_server_path": "",
      "file_directory": "2023/03/30",
      "files_thumbs_path": "",
      "file_thumbs_count": "",
      "has_hq": "no",
      "filegrp_size": "",
      "process_status": 0,
      "video_version": "2.7",
      "extras": "",
      "subscription_email": "pending",
      "thumbs_version": "3.0",
      "re_conv_status": "",
      "conv_progress": "",
      "is_premium": "no",
      "override_default_monetization": 0,
      "credits_required": null,
      "rental_hours": 0,
      "premium_cid": 0,
      "in_editor_pick": "no",
      "has_subs": "no",
      "total_subs": 0,
      "last_sub_num": 0,
      "live": "https://tes.ottervideo.ca/BBC-Lifestyle/video.m3u8",
      "udp_live": "",
      "force_hls_http_url": "https://tes.ottervideo.ca/BBC-Lifestyle/video.m3u8",
      "start_published_date": "2023-03-30 12:30:02",
      "end_published_date": null,
      "has_sprite": "no",
      "version": 1,
      "has_resulotion": "no",
      "aws_service_id": 0,
      "aws_cdn": "",
      "aws_thumb_path": "",
      "license_by": "",
      "is_channeHome": "no",
      "super_feature": 0,
      "is_avod": 1,
      "is_tvod": 0,
      "pre_order": 0,
      "live_status": 0,
      "deleted_at": null,
      "content_type": 4,
      "is_360": 0,
      "projection_type": "NONE",
      "epg_channel_id": "",
      "drm_protected": "no",
      "epg_url": "",
      "content_language": null,
      "dvr_url": "",
      "dvr_backup_timezone": "",
      "dvr_backup_duration": "0",
      "epg_dvr_catchup_url": "",
      "mpaa_rating": null,
      "content_rating_tags": null,
      "logo": "https://vcz-tesvideo-cloud-vodlix-com.b-cdn.net/u/tesvideo/files/video_logos/2023/03/30/1680161283OFlIZvF29a.png",
      "portrait_thumbs": {
        "original": "https://vcz-tesvideo-cloud-vodlix-com.b-cdn.net/u/tesvideo/files/thumbs/2023/03/30/1680161283OFlIZvF29a-original-portrait.jpg",
        "160x240": "https://vcz-tesvideo-cloud-vodlix-com.b-cdn.net/u/tesvideo/files/thumbs/2023/03/30/1680161283OFlIZvF29a-160x240-portrait.jpg",
        "240x360": "https://vcz-tesvideo-cloud-vodlix-com.b-cdn.net/u/tesvideo/files/thumbs/2023/03/30/1680161283OFlIZvF29a-240x360-portrait.jpg",
        "320x480": "https://vcz-tesvideo-cloud-vodlix-com.b-cdn.net/u/tesvideo/files/thumbs/2023/03/30/1680161283OFlIZvF29a-320x480-portrait.jpg",
        "480x720": "https://vcz-tesvideo-cloud-vodlix-com.b-cdn.net/u/tesvideo/files/thumbs/2023/03/30/1680161283OFlIZvF29a-480x720-portrait.jpg",
        "720x1080": "https://vcz-tesvideo-cloud-vodlix-com.b-cdn.net/u/tesvideo/files/thumbs/2023/03/30/1680161283OFlIZvF29a-720x1080-portrait.jpg"
      },
      "thumbs": {
        "original": "https://vcz-tesvideo-cloud-vodlix-com.b-cdn.net/u/tesvideo/files/thumbs/2023/03/30/1680161283OFlIZvF29a-original-gcLkptAF.jpg",
        "168x105": "https://vcz-tesvideo-cloud-vodlix-com.b-cdn.net/u/tesvideo/files/thumbs/2023/03/30/1680161283OFlIZvF29a-168x105-gcLkptAF.jpg",
        "416x260": "https://vcz-tesvideo-cloud-vodlix-com.b-cdn.net/u/tesvideo/files/thumbs/2023/03/30/1680161283OFlIZvF29a-416x260-gcLkptAF.jpg",
        "632x395": "https://vcz-tesvideo-cloud-vodlix-com.b-cdn.net/u/tesvideo/files/thumbs/2023/03/30/1680161283OFlIZvF29a-632x395-gcLkptAF.jpg",
        "768x432": "https://vcz-tesvideo-cloud-vodlix-com.b-cdn.net/u/tesvideo/files/thumbs/2023/03/30/1680161283OFlIZvF29a-768x432-gcLkptAF.jpg",
        "1280x720": "https://vcz-tesvideo-cloud-vodlix-com.b-cdn.net/u/tesvideo/files/thumbs/2023/03/30/1680161283OFlIZvF29a-1280x720-gcLkptAF.jpg",
        "1920x1080": "https://vcz-tesvideo-cloud-vodlix-com.b-cdn.net/u/tesvideo/files/thumbs/2023/03/30/1680161283OFlIZvF29a-1920x1080-gcLkptAF.jpg",
        "200x288": "https://vcz-tesvideo-cloud-vodlix-com.b-cdn.net/u/tesvideo/files/thumbs/2023/03/30/1680161283OFlIZvF29a-200x288-gcLkptAF.jpg"
      },
      "gif": null,
      "files": [
        "https://tes.ottervideo.ca/BBC-Lifestyle/video.m3u8"
      ],
      "watch_url": "/watch/4514",
      "initials": "<?xml version=\"1.0\" encoding=\"utf-8\"?><svg width=\"48\" height=\"48\" xmlns=\"http://www.w3.org/2000/svg\" xmlns:xlink=\"http://www.w3.org/1999/xlink\"><circle cx=\"24\" cy=\"24\" r=\"24\" style=\"fill: none\" /><text x=\"50%\" y=\"50%\" dy=\".1em\" fill=\"#8b5d5d\" font-size=\"24\" text-anchor=\"middle\" dominant-baseline=\"middle\" style=\"font-family: OpenSans, sans-serif; line-height: 1\">BL</text></svg>",
      "year": "2023",
      "duration_in_seconds": "0",
      "rate": 0,
      "trailers": null,
      "fav_id": null,
      "is_fav": null,
      "url": "/watch/4514",
      "shareable": "https://trutv.transworld-home.com/watch/4514",
      "copy_url": "https://tesvideo.cloud.vodlix.com/movies/title/4514",
      "categories": [
        {
          "category_id": 17,
          "parent_id": 0,
          "category_name": "LifeStyle",
          "category_order": 47,
          "category_desc": "LifeStyle",
          "date_added": "2022-11-22 15:59:37",
          "category_thumb": "",
          "featured": "no",
          "isdefault": "no",
          "navbar": "no",
          "is_trailer": 0,
          "meta_title": "LifeStyle",
          "meta_description": "LifeStyle",
          "meta_keywords": "LifeStyle",
          "is_video": 0,
          "is_series": 0,
          "is_live": 1
        }
      ],
      "channel_number": 312,
      "max_resolution": "1080p",
      "square_thumbs": {
        "original": "https://vcz-tesvideo-cloud-vodlix-com.b-cdn.net/u/tesvideo/files/thumbs/2023/03/30/1680161283OFlIZvF29a-original-square.jpg",
        "300x300": "https://vcz-tesvideo-cloud-vodlix-com.b-cdn.net/u/tesvideo/files/thumbs/2023/03/30/1680161283OFlIZvF29a-300x300-square.jpg",
        "512x512": "https://vcz-tesvideo-cloud-vodlix-com.b-cdn.net/u/tesvideo/files/thumbs/2023/03/30/1680161283OFlIZvF29a-512x512-square.jpg",
        "1024x1024": "https://vcz-tesvideo-cloud-vodlix-com.b-cdn.net/u/tesvideo/files/thumbs/2023/03/30/1680161283OFlIZvF29a-1024x1024-square.jpg"
      },
      "interval": " 0s",
      "price_tag": null,
      "show_premium_badge": false,
      "can_pre_order": false,
      "availability_date": null,
      "content_type_label": "live"
    },
    {
      "videoid": 4483,
      "videokey": "RW851WGH2RW9",
      "video_password": null,
      "video_users": "",
      "username": "",
      "userid": 1,
      "partner_id": null,
      "maturity_level": "all",
      "title": "Madni Tv",
      "file_name": "16801563340JzJCW4nfa",
      "file_type": 2,
      "description": "Madni Tv",
      "tags": "unknown",
      "category": "#3# ",
      "category_parents": "",
      "broadcast": "public",
      "location": "0",
      "datecreated": "2023-03-30",
      "country": "0",
      "blocked_countries": "",
      "allowed_countries": "0",
      "sprite_count": 0,
      "season_id": 0,
      "series_id": 0,
      "sequence": 344,
      "allow_embedding": "",
      "rating": 0,
      "rated_by": "0",
      "voter_ids": "",
      "featured": "no",
      "featured_order": null,
      "featured_date": "0000-00-00 00:00:00",
      "featured_description": "",
      "allow_rating": "yes",
      "allow_comments": "yes",
      "comments_count": 0,
      "last_commented": null,
      "active": "yes",
      "favourite_count": "0",
      "playlist_count": "0",
      "views": 0,
      "last_viewed": "0000-00-00 00:00:00",
      "date_added": "2023-03-30",
      "flagged": "no",
      "duration": " 0s",
      "status": "Successful",
      "failed_reason": "none",
      "default_thumb": 207649,
      "aspect_ratio": "",
      "embed_code": "",
      "refer_url": "",
      "downloads": 0,
      "uploader_ip": "110.93.192.18",
      "mass_embed_status": "no",
      "unique_embed_code": "",
      "remote_play_url": "",
      "video_files": "",
      "server_ip": "",
      "file_server_path": "",
      "file_directory": "2023/03/30",
      "files_thumbs_path": "",
      "file_thumbs_count": "",
      "has_hq": "no",
      "filegrp_size": "",
      "process_status": 0,
      "video_version": "2.7",
      "extras": "",
      "subscription_email": "pending",
      "thumbs_version": "3.0",
      "re_conv_status": "",
      "conv_progress": "",
      "is_premium": "no",
      "override_default_monetization": 0,
      "credits_required": null,
      "rental_hours": 0,
      "premium_cid": 0,
      "in_editor_pick": "no",
      "has_subs": "no",
      "total_subs": 0,
      "last_sub_num": 0,
      "live": "https://tes.ottervideo.ca/Madni-Tv/video.m3u8",
      "udp_live": "",
      "force_hls_http_url": "https://tes.ottervideo.ca/Madni-Tv/video.m3u8",
      "start_published_date": "2023-03-30 11:08:49",
      "end_published_date": null,
      "has_sprite": "no",
      "version": 1,
      "has_resulotion": "no",
      "aws_service_id": 0,
      "aws_cdn": "",
      "aws_thumb_path": "",
      "license_by": "",
      "is_channeHome": "no",
      "super_feature": 0,
      "is_avod": 1,
      "is_tvod": 0,
      "pre_order": 0,
      "live_status": 0,
      "deleted_at": null,
      "content_type": 4,
      "is_360": 0,
      "projection_type": "NONE",
      "epg_channel_id": "",
      "drm_protected": "no",
      "epg_url": "",
      "content_language": null,
      "dvr_url": "",
      "dvr_backup_timezone": "",
      "dvr_backup_duration": "0",
      "epg_dvr_catchup_url": "",
      "mpaa_rating": null,
      "content_rating_tags": null,
      "logo": "https://vcz-tesvideo-cloud-vodlix-com.b-cdn.net/u/tesvideo/files/video_logos/2023/03/30/16801563340JzJCW4nfa.png",
      "portrait_thumbs": {
        "original": "https://vcz-tesvideo-cloud-vodlix-com.b-cdn.net/u/tesvideo/files/thumbs/2023/03/30/16801563340JzJCW4nfa-original-portrait.jpg",
        "160x240": "https://vcz-tesvideo-cloud-vodlix-com.b-cdn.net/u/tesvideo/files/thumbs/2023/03/30/16801563340JzJCW4nfa-160x240-portrait.jpg",
        "240x360": "https://vcz-tesvideo-cloud-vodlix-com.b-cdn.net/u/tesvideo/files/thumbs/2023/03/30/16801563340JzJCW4nfa-240x360-portrait.jpg",
        "320x480": "https://vcz-tesvideo-cloud-vodlix-com.b-cdn.net/u/tesvideo/files/thumbs/2023/03/30/16801563340JzJCW4nfa-320x480-portrait.jpg",
        "480x720": "https://vcz-tesvideo-cloud-vodlix-com.b-cdn.net/u/tesvideo/files/thumbs/2023/03/30/16801563340JzJCW4nfa-480x720-portrait.jpg",
        "720x1080": "https://vcz-tesvideo-cloud-vodlix-com.b-cdn.net/u/tesvideo/files/thumbs/2023/03/30/16801563340JzJCW4nfa-720x1080-portrait.jpg"
      },
      "thumbs": {
        "original": "https://vcz-tesvideo-cloud-vodlix-com.b-cdn.net/u/tesvideo/files/thumbs/2023/03/30/16801563340JzJCW4nfa-original-z5x3Otj0.jpg",
        "168x105": "https://vcz-tesvideo-cloud-vodlix-com.b-cdn.net/u/tesvideo/files/thumbs/2023/03/30/16801563340JzJCW4nfa-168x105-z5x3Otj0.jpg",
        "416x260": "https://vcz-tesvideo-cloud-vodlix-com.b-cdn.net/u/tesvideo/files/thumbs/2023/03/30/16801563340JzJCW4nfa-416x260-z5x3Otj0.jpg",
        "632x395": "https://vcz-tesvideo-cloud-vodlix-com.b-cdn.net/u/tesvideo/files/thumbs/2023/03/30/16801563340JzJCW4nfa-632x395-z5x3Otj0.jpg",
        "768x432": "https://vcz-tesvideo-cloud-vodlix-com.b-cdn.net/u/tesvideo/files/thumbs/2023/03/30/16801563340JzJCW4nfa-768x432-z5x3Otj0.jpg",
        "1280x720": "https://vcz-tesvideo-cloud-vodlix-com.b-cdn.net/u/tesvideo/files/thumbs/2023/03/30/16801563340JzJCW4nfa-1280x720-z5x3Otj0.jpg",
        "1920x1080": "https://vcz-tesvideo-cloud-vodlix-com.b-cdn.net/u/tesvideo/files/thumbs/2023/03/30/16801563340JzJCW4nfa-1920x1080-z5x3Otj0.jpg",
        "200x288": "https://vcz-tesvideo-cloud-vodlix-com.b-cdn.net/u/tesvideo/files/thumbs/2023/03/30/16801563340JzJCW4nfa-200x288-z5x3Otj0.jpg"
      },
      "gif": null,
      "files": [
        "https://tes.ottervideo.ca/Madni-Tv/video.m3u8"
      ],
      "watch_url": "/watch/4483",
      "initials": "<?xml version=\"1.0\" encoding=\"utf-8\"?><svg width=\"48\" height=\"48\" xmlns=\"http://www.w3.org/2000/svg\" xmlns:xlink=\"http://www.w3.org/1999/xlink\"><circle cx=\"24\" cy=\"24\" r=\"24\" style=\"fill: none\" /><text x=\"50%\" y=\"50%\" dy=\".1em\" fill=\"#8b5d5d\" font-size=\"24\" text-anchor=\"middle\" dominant-baseline=\"middle\" style=\"font-family: OpenSans, sans-serif; line-height: 1\">MT</text></svg>",
      "year": "2023",
      "duration_in_seconds": "0",
      "rate": 0,
      "trailers": null,
      "fav_id": null,
      "is_fav": null,
      "url": "/watch/4483",
      "shareable": "https://trutv.transworld-home.com/watch/4483",
      "copy_url": "https://tesvideo.cloud.vodlix.com/movies/title/4483",
      "categories": [
        {
          "category_id": 3,
          "parent_id": 0,
          "category_name": "Religious",
          "category_order": 48,
          "category_desc": "Religious",
          "date_added": "2022-11-07 05:19:41",
          "category_thumb": "",
          "featured": "no",
          "isdefault": "no",
          "navbar": "no",
          "is_trailer": 0,
          "meta_title": null,
          "meta_description": null,
          "meta_keywords": "Religious",
          "is_video": 0,
          "is_series": 0,
          "is_live": 1
        }
      ],
      "channel_number": 344,
      "max_resolution": "1080p",
      "square_thumbs": {
        "original": "https://vcz-tesvideo-cloud-vodlix-com.b-cdn.net/u/tesvideo/files/thumbs/2023/03/30/16801563340JzJCW4nfa-original-square.jpg",
        "300x300": "https://vcz-tesvideo-cloud-vodlix-com.b-cdn.net/u/tesvideo/files/thumbs/2023/03/30/16801563340JzJCW4nfa-300x300-square.jpg",
        "512x512": "https://vcz-tesvideo-cloud-vodlix-com.b-cdn.net/u/tesvideo/files/thumbs/2023/03/30/16801563340JzJCW4nfa-512x512-square.jpg",
        "1024x1024": "https://vcz-tesvideo-cloud-vodlix-com.b-cdn.net/u/tesvideo/files/thumbs/2023/03/30/16801563340JzJCW4nfa-1024x1024-square.jpg"
      },
      "interval": " 0s",
      "price_tag": null,
      "show_premium_badge": false,
      "can_pre_order": false,
      "availability_date": null,
      "content_type_label": "live"
    },
    {
      "videoid": 4482,
      "videokey": "6A4KYXH1811Y",
      "video_password": null,
      "video_users": "",
      "username": "",
      "userid": 1,
      "partner_id": null,
      "maturity_level": "all",
      "title": "Peace-Tv-Eng",
      "file_name": "1680105883jk9hNxV4w3",
      "file_type": 2,
      "description": "Peace-Tv-Eng",
      "tags": "unknown",
      "category": "#3# ",
      "category_parents": "",
      "broadcast": "public",
      "location": "0",
      "datecreated": "2023-03-29",
      "country": "0",
      "blocked_countries": "",
      "allowed_countries": "0",
      "sprite_count": 0,
      "season_id": 0,
      "series_id": 0,
      "sequence": 346,
      "allow_embedding": "",
      "rating": 0,
      "rated_by": "0",
      "voter_ids": "",
      "featured": "no",
      "featured_order": null,
      "featured_date": "0000-00-00 00:00:00",
      "featured_description": "",
      "allow_rating": "yes",
      "allow_comments": "yes",
      "comments_count": 0,
      "last_commented": null,
      "active": "yes",
      "favourite_count": "0",
      "playlist_count": "0",
      "views": 1,
      "last_viewed": "0000-00-00 00:00:00",
      "date_added": "2023-03-29",
      "flagged": "no",
      "duration": " 0s",
      "status": "Successful",
      "failed_reason": "none",
      "default_thumb": 207630,
      "aspect_ratio": "",
      "embed_code": "",
      "refer_url": "",
      "downloads": 0,
      "uploader_ip": "110.93.192.18",
      "mass_embed_status": "no",
      "unique_embed_code": "",
      "remote_play_url": "",
      "video_files": "",
      "server_ip": "",
      "file_server_path": "",
      "file_directory": "2023/03/29",
      "files_thumbs_path": "",
      "file_thumbs_count": "",
      "has_hq": "no",
      "filegrp_size": "",
      "process_status": 0,
      "video_version": "2.7",
      "extras": "",
      "subscription_email": "pending",
      "thumbs_version": "3.0",
      "re_conv_status": "",
      "conv_progress": "",
      "is_premium": "no",
      "override_default_monetization": 0,
      "credits_required": null,
      "rental_hours": 0,
      "premium_cid": 0,
      "in_editor_pick": "no",
      "has_subs": "no",
      "total_subs": 0,
      "last_sub_num": 0,
      "live": "https://tes.ottervideo.ca/Peace-Tv-Eng/video.m3u8",
      "udp_live": "",
      "force_hls_http_url": "https://tes.ottervideo.ca/Peace-Tv-Eng/video.m3u8",
      "start_published_date": "2023-03-29 21:13:54",
      "end_published_date": null,
      "has_sprite": "no",
      "version": 1,
      "has_resulotion": "no",
      "aws_service_id": 0,
      "aws_cdn": "",
      "aws_thumb_path": "",
      "license_by": "",
      "is_channeHome": "no",
      "super_feature": 0,
      "is_avod": 1,
      "is_tvod": 0,
      "pre_order": 0,
      "live_status": 0,
      "deleted_at": null,
      "content_type": 4,
      "is_360": 0,
      "projection_type": "NONE",
      "epg_channel_id": "",
      "drm_protected": "no",
      "epg_url": "",
      "content_language": null,
      "dvr_url": "",
      "dvr_backup_timezone": "",
      "dvr_backup_duration": "0",
      "epg_dvr_catchup_url": "",
      "mpaa_rating": null,
      "content_rating_tags": null,
      "logo": "https://vcz-tesvideo-cloud-vodlix-com.b-cdn.net/u/tesvideo/files/video_logos/2023/03/29/1680105883jk9hNxV4w3.png",
      "portrait_thumbs": {
        "original": "https://vcz-tesvideo-cloud-vodlix-com.b-cdn.net/u/tesvideo/files/thumbs/2023/03/29/1680105883jk9hNxV4w3-original-portrait.jpg",
        "160x240": "https://vcz-tesvideo-cloud-vodlix-com.b-cdn.net/u/tesvideo/files/thumbs/2023/03/29/1680105883jk9hNxV4w3-160x240-portrait.jpg",
        "240x360": "https://vcz-tesvideo-cloud-vodlix-com.b-cdn.net/u/tesvideo/files/thumbs/2023/03/29/1680105883jk9hNxV4w3-240x360-portrait.jpg",
        "320x480": "https://vcz-tesvideo-cloud-vodlix-com.b-cdn.net/u/tesvideo/files/thumbs/2023/03/29/1680105883jk9hNxV4w3-320x480-portrait.jpg",
        "480x720": "https://vcz-tesvideo-cloud-vodlix-com.b-cdn.net/u/tesvideo/files/thumbs/2023/03/29/1680105883jk9hNxV4w3-480x720-portrait.jpg",
        "720x1080": "https://vcz-tesvideo-cloud-vodlix-com.b-cdn.net/u/tesvideo/files/thumbs/2023/03/29/1680105883jk9hNxV4w3-720x1080-portrait.jpg"
      },
      "thumbs": {
        "original": "https://vcz-tesvideo-cloud-vodlix-com.b-cdn.net/u/tesvideo/files/thumbs/2023/03/29/1680105883jk9hNxV4w3-original-oCIQowlf.jpg",
        "168x105": "https://vcz-tesvideo-cloud-vodlix-com.b-cdn.net/u/tesvideo/files/thumbs/2023/03/29/1680105883jk9hNxV4w3-168x105-oCIQowlf.jpg",
        "416x260": "https://vcz-tesvideo-cloud-vodlix-com.b-cdn.net/u/tesvideo/files/thumbs/2023/03/29/1680105883jk9hNxV4w3-416x260-oCIQowlf.jpg",
        "632x395": "https://vcz-tesvideo-cloud-vodlix-com.b-cdn.net/u/tesvideo/files/thumbs/2023/03/29/1680105883jk9hNxV4w3-632x395-oCIQowlf.jpg",
        "768x432": "https://vcz-tesvideo-cloud-vodlix-com.b-cdn.net/u/tesvideo/files/thumbs/2023/03/29/1680105883jk9hNxV4w3-768x432-oCIQowlf.jpg",
        "1280x720": "https://vcz-tesvideo-cloud-vodlix-com.b-cdn.net/u/tesvideo/files/thumbs/2023/03/29/1680105883jk9hNxV4w3-1280x720-oCIQowlf.jpg",
        "1920x1080": "https://vcz-tesvideo-cloud-vodlix-com.b-cdn.net/u/tesvideo/files/thumbs/2023/03/29/1680105883jk9hNxV4w3-1920x1080-oCIQowlf.jpg",
        "200x288": "https://vcz-tesvideo-cloud-vodlix-com.b-cdn.net/u/tesvideo/files/thumbs/2023/03/29/1680105883jk9hNxV4w3-200x288-oCIQowlf.jpg"
      },
      "gif": null,
      "files": [
        "https://tes.ottervideo.ca/Peace-Tv-Eng/video.m3u8"
      ],
      "watch_url": "/watch/4482",
      "initials": "<?xml version=\"1.0\" encoding=\"utf-8\"?><svg width=\"48\" height=\"48\" xmlns=\"http://www.w3.org/2000/svg\" xmlns:xlink=\"http://www.w3.org/1999/xlink\"><circle cx=\"24\" cy=\"24\" r=\"24\" style=\"fill: none\" /><text x=\"50%\" y=\"50%\" dy=\".1em\" fill=\"#8b5d5d\" font-size=\"24\" text-anchor=\"middle\" dominant-baseline=\"middle\" style=\"font-family: OpenSans, sans-serif; line-height: 1\">PE</text></svg>",
      "year": "2023",
      "duration_in_seconds": "0",
      "rate": 0,
      "trailers": null,
      "fav_id": null,
      "is_fav": null,
      "url": "/watch/4482",
      "shareable": "https://trutv.transworld-home.com/watch/4482",
      "copy_url": "https://tesvideo.cloud.vodlix.com/movies/title/4482",
      "categories": [
        {
          "category_id": 3,
          "parent_id": 0,
          "category_name": "Religious",
          "category_order": 48,
          "category_desc": "Religious",
          "date_added": "2022-11-07 05:19:41",
          "category_thumb": "",
          "featured": "no",
          "isdefault": "no",
          "navbar": "no",
          "is_trailer": 0,
          "meta_title": null,
          "meta_description": null,
          "meta_keywords": "Religious",
          "is_video": 0,
          "is_series": 0,
          "is_live": 1
        }
      ],
      "channel_number": 346,
      "max_resolution": "1080p",
      "square_thumbs": {
        "original": "https://vcz-tesvideo-cloud-vodlix-com.b-cdn.net/u/tesvideo/files/thumbs/2023/03/29/1680105883jk9hNxV4w3-original-square.jpg",
        "300x300": "https://vcz-tesvideo-cloud-vodlix-com.b-cdn.net/u/tesvideo/files/thumbs/2023/03/29/1680105883jk9hNxV4w3-300x300-square.jpg",
        "512x512": "https://vcz-tesvideo-cloud-vodlix-com.b-cdn.net/u/tesvideo/files/thumbs/2023/03/29/1680105883jk9hNxV4w3-512x512-square.jpg",
        "1024x1024": "https://vcz-tesvideo-cloud-vodlix-com.b-cdn.net/u/tesvideo/files/thumbs/2023/03/29/1680105883jk9hNxV4w3-1024x1024-square.jpg"
      },
      "interval": " 0s",
      "price_tag": null,
      "show_premium_badge": false,
      "can_pre_order": false,
      "availability_date": null,
      "content_type_label": "live"
    },
    {
      "videoid": 4481,
      "videokey": "7W4DKN9M5AYX",
      "video_password": null,
      "video_users": "",
      "username": "",
      "userid": 1,
      "partner_id": null,
      "maturity_level": "all",
      "title": "ARY-Music",
      "file_name": "1680056075JLVWtPv2qb",
      "file_type": 2,
      "description": "ARY-Music",
      "tags": "ary-music,music",
      "category": "#18# ",
      "category_parents": "",
      "broadcast": "public",
      "location": "0",
      "datecreated": "2023-03-29",
      "country": "0",
      "blocked_countries": "#0# ",
      "allowed_countries": "0",
      "sprite_count": 0,
      "season_id": 0,
      "series_id": 0,
      "sequence": 284,
      "allow_embedding": "",
      "rating": 0,
      "rated_by": "0",
      "voter_ids": "",
      "featured": "no",
      "featured_order": null,
      "featured_date": "0000-00-00 00:00:00",
      "featured_description": "",
      "allow_rating": "yes",
      "allow_comments": "yes",
      "comments_count": 0,
      "last_commented": null,
      "active": "yes",
      "favourite_count": "0",
      "playlist_count": "0",
      "views": 0,
      "last_viewed": "0000-00-00 00:00:00",
      "date_added": "2023-03-29",
      "flagged": "no",
      "duration": " 0s",
      "status": "Successful",
      "failed_reason": "none",
      "default_thumb": 207481,
      "aspect_ratio": "",
      "embed_code": "",
      "refer_url": "",
      "downloads": 0,
      "uploader_ip": "110.93.192.18",
      "mass_embed_status": "no",
      "unique_embed_code": "",
      "remote_play_url": "",
      "video_files": "",
      "server_ip": "",
      "file_server_path": "",
      "file_directory": "2023/03/29",
      "files_thumbs_path": "",
      "file_thumbs_count": "",
      "has_hq": "no",
      "filegrp_size": "",
      "process_status": 0,
      "video_version": "2.7",
      "extras": "",
      "subscription_email": "pending",
      "thumbs_version": "3.0",
      "re_conv_status": "",
      "conv_progress": "",
      "is_premium": "no",
      "override_default_monetization": 0,
      "credits_required": null,
      "rental_hours": 0,
      "premium_cid": 0,
      "in_editor_pick": "no",
      "has_subs": "no",
      "total_subs": 0,
      "last_sub_num": 0,
      "live": "https://tes.ottervideo.ca/Ary-Music/video.m3u8",
      "udp_live": "",
      "force_hls_http_url": "https://tes.ottervideo.ca/Ary-Music/video.m3u8",
      "start_published_date": "2023-03-30 12:27:03",
      "end_published_date": null,
      "has_sprite": "no",
      "version": 1,
      "has_resulotion": "no",
      "aws_service_id": 0,
      "aws_cdn": "",
      "aws_thumb_path": "",
      "license_by": "",
      "is_channeHome": "no",
      "super_feature": 0,
      "is_avod": 1,
      "is_tvod": 0,
      "pre_order": 0,
      "live_status": 0,
      "deleted_at": null,
      "content_type": 4,
      "is_360": 0,
      "projection_type": "NONE",
      "epg_channel_id": "",
      "drm_protected": "no",
      "epg_url": "",
      "content_language": null,
      "dvr_url": "",
      "dvr_backup_timezone": "",
      "dvr_backup_duration": "0",
      "epg_dvr_catchup_url": "",
      "mpaa_rating": null,
      "content_rating_tags": null,
      "logo": "https://vcz-tesvideo-cloud-vodlix-com.b-cdn.net/u/tesvideo/files/video_logos/2023/03/29/1680056075JLVWtPv2qb.png",
      "portrait_thumbs": {
        "original": "https://vcz-tesvideo-cloud-vodlix-com.b-cdn.net/u/tesvideo/files/thumbs/2023/03/29/1680056075JLVWtPv2qb-original-portrait.jpg",
        "160x240": "https://vcz-tesvideo-cloud-vodlix-com.b-cdn.net/u/tesvideo/files/thumbs/2023/03/29/1680056075JLVWtPv2qb-160x240-portrait.jpg",
        "240x360": "https://vcz-tesvideo-cloud-vodlix-com.b-cdn.net/u/tesvideo/files/thumbs/2023/03/29/1680056075JLVWtPv2qb-240x360-portrait.jpg",
        "320x480": "https://vcz-tesvideo-cloud-vodlix-com.b-cdn.net/u/tesvideo/files/thumbs/2023/03/29/1680056075JLVWtPv2qb-320x480-portrait.jpg",
        "480x720": "https://vcz-tesvideo-cloud-vodlix-com.b-cdn.net/u/tesvideo/files/thumbs/2023/03/29/1680056075JLVWtPv2qb-480x720-portrait.jpg",
        "720x1080": "https://vcz-tesvideo-cloud-vodlix-com.b-cdn.net/u/tesvideo/files/thumbs/2023/03/29/1680056075JLVWtPv2qb-720x1080-portrait.jpg"
      },
      "thumbs": {
        "original": "https://vcz-tesvideo-cloud-vodlix-com.b-cdn.net/u/tesvideo/files/thumbs/2023/03/29/1680056075JLVWtPv2qb-original-UxVxYGM8.jpg",
        "168x105": "https://vcz-tesvideo-cloud-vodlix-com.b-cdn.net/u/tesvideo/files/thumbs/2023/03/29/1680056075JLVWtPv2qb-168x105-UxVxYGM8.jpg",
        "416x260": "https://vcz-tesvideo-cloud-vodlix-com.b-cdn.net/u/tesvideo/files/thumbs/2023/03/29/1680056075JLVWtPv2qb-416x260-UxVxYGM8.jpg",
        "632x395": "https://vcz-tesvideo-cloud-vodlix-com.b-cdn.net/u/tesvideo/files/thumbs/2023/03/29/1680056075JLVWtPv2qb-632x395-UxVxYGM8.jpg",
        "768x432": "https://vcz-tesvideo-cloud-vodlix-com.b-cdn.net/u/tesvideo/files/thumbs/2023/03/29/1680056075JLVWtPv2qb-768x432-UxVxYGM8.jpg",
        "1280x720": "https://vcz-tesvideo-cloud-vodlix-com.b-cdn.net/u/tesvideo/files/thumbs/2023/03/29/1680056075JLVWtPv2qb-1280x720-UxVxYGM8.jpg",
        "1920x1080": "https://vcz-tesvideo-cloud-vodlix-com.b-cdn.net/u/tesvideo/files/thumbs/2023/03/29/1680056075JLVWtPv2qb-1920x1080-UxVxYGM8.jpg",
        "200x288": "https://vcz-tesvideo-cloud-vodlix-com.b-cdn.net/u/tesvideo/files/thumbs/2023/03/29/1680056075JLVWtPv2qb-200x288-UxVxYGM8.jpg"
      },
      "gif": null,
      "files": [
        "https://tes.ottervideo.ca/Ary-Music/video.m3u8"
      ],
      "watch_url": "/watch/4481",
      "initials": "<?xml version=\"1.0\" encoding=\"utf-8\"?><svg width=\"48\" height=\"48\" xmlns=\"http://www.w3.org/2000/svg\" xmlns:xlink=\"http://www.w3.org/1999/xlink\"><circle cx=\"24\" cy=\"24\" r=\"24\" style=\"fill: none\" /><text x=\"50%\" y=\"50%\" dy=\".1em\" fill=\"#8b5d5d\" font-size=\"24\" text-anchor=\"middle\" dominant-baseline=\"middle\" style=\"font-family: OpenSans, sans-serif; line-height: 1\">AM</text></svg>",
      "year": "2023",
      "duration_in_seconds": "0",
      "rate": 0,
      "trailers": null,
      "fav_id": null,
      "is_fav": null,
      "url": "/watch/4481",
      "shareable": "https://trutv.transworld-home.com/watch/4481",
      "copy_url": "https://tesvideo.cloud.vodlix.com/movies/title/4481",
      "categories": [
        {
          "category_id": 18,
          "parent_id": 0,
          "category_name": "Music",
          "category_order": 45,
          "category_desc": "Music",
          "date_added": "2022-11-22 16:01:22",
          "category_thumb": "",
          "featured": "no",
          "isdefault": "no",
          "navbar": "no",
          "is_trailer": 0,
          "meta_title": "Music",
          "meta_description": "Music",
          "meta_keywords": "Music",
          "is_video": 0,
          "is_series": 0,
          "is_live": 1
        }
      ],
      "channel_number": 284,
      "max_resolution": "1080p",
      "square_thumbs": {
        "original": "https://vcz-tesvideo-cloud-vodlix-com.b-cdn.net/u/tesvideo/files/thumbs/2023/03/29/1680056075JLVWtPv2qb-original-square.jpg",
        "300x300": "https://vcz-tesvideo-cloud-vodlix-com.b-cdn.net/u/tesvideo/files/thumbs/2023/03/29/1680056075JLVWtPv2qb-300x300-square.jpg",
        "512x512": "https://vcz-tesvideo-cloud-vodlix-com.b-cdn.net/u/tesvideo/files/thumbs/2023/03/29/1680056075JLVWtPv2qb-512x512-square.jpg",
        "1024x1024": "https://vcz-tesvideo-cloud-vodlix-com.b-cdn.net/u/tesvideo/files/thumbs/2023/03/29/1680056075JLVWtPv2qb-1024x1024-square.jpg"
      },
      "interval": " 0s",
      "price_tag": null,
      "show_premium_badge": false,
      "can_pre_order": false,
      "availability_date": null,
      "content_type_label": "live"
    },
    {
      "videoid": 4480,
      "videokey": "NORX72S92Y54",
      "video_password": null,
      "video_users": "",
      "username": "",
      "userid": 1,
      "partner_id": null,
      "maturity_level": "all",
      "title": "History 2 HD",
      "file_name": "16800554055DhDkomXvU",
      "file_type": 2,
      "description": "History 2 HD",
      "tags": "history 2 hd,documentary",
      "category": "#6# ",
      "category_parents": "",
      "broadcast": "public",
      "location": "0",
      "datecreated": "2023-03-29",
      "country": "0",
      "blocked_countries": "#0# ",
      "allowed_countries": "0",
      "sprite_count": 0,
      "season_id": 0,
      "series_id": 0,
      "sequence": 266,
      "allow_embedding": "",
      "rating": 0,
      "rated_by": "0",
      "voter_ids": "",
      "featured": "no",
      "featured_order": null,
      "featured_date": "0000-00-00 00:00:00",
      "featured_description": "",
      "allow_rating": "yes",
      "allow_comments": "yes",
      "comments_count": 0,
      "last_commented": null,
      "active": "yes",
      "favourite_count": "0",
      "playlist_count": "0",
      "views": 0,
      "last_viewed": "0000-00-00 00:00:00",
      "date_added": "2023-03-29",
      "flagged": "no",
      "duration": " 0s",
      "status": "Successful",
      "failed_reason": "none",
      "default_thumb": 207462,
      "aspect_ratio": "",
      "embed_code": "",
      "refer_url": "",
      "downloads": 0,
      "uploader_ip": "110.93.192.18",
      "mass_embed_status": "no",
      "unique_embed_code": "",
      "remote_play_url": "",
      "video_files": "",
      "server_ip": "",
      "file_server_path": "",
      "file_directory": "2023/03/29",
      "files_thumbs_path": "",
      "file_thumbs_count": "",
      "has_hq": "no",
      "filegrp_size": "",
      "process_status": 0,
      "video_version": "2.7",
      "extras": "",
      "subscription_email": "pending",
      "thumbs_version": "3.0",
      "re_conv_status": "",
      "conv_progress": "",
      "is_premium": "no",
      "override_default_monetization": 0,
      "credits_required": null,
      "rental_hours": 0,
      "premium_cid": 0,
      "in_editor_pick": "no",
      "has_subs": "no",
      "total_subs": 0,
      "last_sub_num": 0,
      "live": "https://tes.ottervideo.ca/H2/video.m3u8",
      "udp_live": "",
      "force_hls_http_url": "https://tes.ottervideo.ca/H2/video.m3u8",
      "start_published_date": "2023-03-29 10:30:32",
      "end_published_date": null,
      "has_sprite": "no",
      "version": 1,
      "has_resulotion": "no",
      "aws_service_id": 0,
      "aws_cdn": "",
      "aws_thumb_path": "",
      "license_by": "",
      "is_channeHome": "no",
      "super_feature": 0,
      "is_avod": 1,
      "is_tvod": 0,
      "pre_order": 0,
      "live_status": 0,
      "deleted_at": null,
      "content_type": 4,
      "is_360": 0,
      "projection_type": "NONE",
      "epg_channel_id": "",
      "drm_protected": "no",
      "epg_url": "",
      "content_language": null,
      "dvr_url": "",
      "dvr_backup_timezone": "",
      "dvr_backup_duration": "0",
      "epg_dvr_catchup_url": "",
      "mpaa_rating": null,
      "content_rating_tags": null,
      "logo": "https://vcz-tesvideo-cloud-vodlix-com.b-cdn.net/u/tesvideo/files/video_logos/2023/03/29/16800554055DhDkomXvU.png",
      "portrait_thumbs": {
        "original": "https://vcz-tesvideo-cloud-vodlix-com.b-cdn.net/u/tesvideo/files/thumbs/2023/03/29/16800554055DhDkomXvU-original-portrait.jpg",
        "160x240": "https://vcz-tesvideo-cloud-vodlix-com.b-cdn.net/u/tesvideo/files/thumbs/2023/03/29/16800554055DhDkomXvU-160x240-portrait.jpg",
        "240x360": "https://vcz-tesvideo-cloud-vodlix-com.b-cdn.net/u/tesvideo/files/thumbs/2023/03/29/16800554055DhDkomXvU-240x360-portrait.jpg",
        "320x480": "https://vcz-tesvideo-cloud-vodlix-com.b-cdn.net/u/tesvideo/files/thumbs/2023/03/29/16800554055DhDkomXvU-320x480-portrait.jpg",
        "480x720": "https://vcz-tesvideo-cloud-vodlix-com.b-cdn.net/u/tesvideo/files/thumbs/2023/03/29/16800554055DhDkomXvU-480x720-portrait.jpg",
        "720x1080": "https://vcz-tesvideo-cloud-vodlix-com.b-cdn.net/u/tesvideo/files/thumbs/2023/03/29/16800554055DhDkomXvU-720x1080-portrait.jpg"
      },
      "thumbs": {
        "original": "https://vcz-tesvideo-cloud-vodlix-com.b-cdn.net/u/tesvideo/files/thumbs/2023/03/29/16800554055DhDkomXvU-original-hXr48H2l.jpg",
        "168x105": "https://vcz-tesvideo-cloud-vodlix-com.b-cdn.net/u/tesvideo/files/thumbs/2023/03/29/16800554055DhDkomXvU-168x105-hXr48H2l.jpg",
        "416x260": "https://vcz-tesvideo-cloud-vodlix-com.b-cdn.net/u/tesvideo/files/thumbs/2023/03/29/16800554055DhDkomXvU-416x260-hXr48H2l.jpg",
        "632x395": "https://vcz-tesvideo-cloud-vodlix-com.b-cdn.net/u/tesvideo/files/thumbs/2023/03/29/16800554055DhDkomXvU-632x395-hXr48H2l.jpg",
        "768x432": "https://vcz-tesvideo-cloud-vodlix-com.b-cdn.net/u/tesvideo/files/thumbs/2023/03/29/16800554055DhDkomXvU-768x432-hXr48H2l.jpg",
        "1280x720": "https://vcz-tesvideo-cloud-vodlix-com.b-cdn.net/u/tesvideo/files/thumbs/2023/03/29/16800554055DhDkomXvU-1280x720-hXr48H2l.jpg",
        "1920x1080": "https://vcz-tesvideo-cloud-vodlix-com.b-cdn.net/u/tesvideo/files/thumbs/2023/03/29/16800554055DhDkomXvU-1920x1080-hXr48H2l.jpg",
        "200x288": "https://vcz-tesvideo-cloud-vodlix-com.b-cdn.net/u/tesvideo/files/thumbs/2023/03/29/16800554055DhDkomXvU-200x288-hXr48H2l.jpg"
      },
      "gif": null,
      "files": [
        "https://tes.ottervideo.ca/H2/video.m3u8"
      ],
      "watch_url": "/watch/4480",
      "initials": "<?xml version=\"1.0\" encoding=\"utf-8\"?><svg width=\"48\" height=\"48\" xmlns=\"http://www.w3.org/2000/svg\" xmlns:xlink=\"http://www.w3.org/1999/xlink\"><circle cx=\"24\" cy=\"24\" r=\"24\" style=\"fill: none\" /><text x=\"50%\" y=\"50%\" dy=\".1em\" fill=\"#8b5d5d\" font-size=\"24\" text-anchor=\"middle\" dominant-baseline=\"middle\" style=\"font-family: OpenSans, sans-serif; line-height: 1\">HH</text></svg>",
      "year": "2023",
      "duration_in_seconds": "0",
      "rate": 0,
      "trailers": null,
      "fav_id": null,
      "is_fav": null,
      "url": "/watch/4480",
      "shareable": "https://trutv.transworld-home.com/watch/4480",
      "copy_url": "https://tesvideo.cloud.vodlix.com/movies/title/4480",
      "categories": [
        {
          "category_id": 6,
          "parent_id": 0,
          "category_name": "Documentary",
          "category_order": 46,
          "category_desc": "Documentary",
          "date_added": "2022-11-07 05:21:19",
          "category_thumb": "",
          "featured": "no",
          "isdefault": "no",
          "navbar": "no",
          "is_trailer": 0,
          "meta_title": null,
          "meta_description": null,
          "meta_keywords": "Documentary",
          "is_video": 0,
          "is_series": 0,
          "is_live": 1
        }
      ],
      "channel_number": 266,
      "max_resolution": "1080p",
      "square_thumbs": {
        "original": "https://vcz-tesvideo-cloud-vodlix-com.b-cdn.net/u/tesvideo/files/thumbs/2023/03/29/16800554055DhDkomXvU-original-square.jpg",
        "300x300": "https://vcz-tesvideo-cloud-vodlix-com.b-cdn.net/u/tesvideo/files/thumbs/2023/03/29/16800554055DhDkomXvU-300x300-square.jpg",
        "512x512": "https://vcz-tesvideo-cloud-vodlix-com.b-cdn.net/u/tesvideo/files/thumbs/2023/03/29/16800554055DhDkomXvU-512x512-square.jpg",
        "1024x1024": "https://vcz-tesvideo-cloud-vodlix-com.b-cdn.net/u/tesvideo/files/thumbs/2023/03/29/16800554055DhDkomXvU-1024x1024-square.jpg"
      },
      "interval": " 0s",
      "price_tag": null,
      "show_premium_badge": false,
      "can_pre_order": false,
      "availability_date": null,
      "content_type_label": "live"
    },
    {
      "videoid": 4479,
      "videokey": "M93KYYGDG4UW",
      "video_password": null,
      "video_users": "",
      "username": "",
      "userid": 1,
      "partner_id": null,
      "maturity_level": "all",
      "title": "Outdoor Channel HD",
      "file_name": "1680054756waqEmr1AFw",
      "file_type": 2,
      "description": "Outdoor Channel HD",
      "tags": "outdoor channel hd,documentary",
      "category": "#6# ",
      "category_parents": "",
      "broadcast": "public",
      "location": "0",
      "datecreated": "2023-03-29",
      "country": "0",
      "blocked_countries": "#0# ",
      "allowed_countries": "0",
      "sprite_count": 0,
      "season_id": 0,
      "series_id": 0,
      "sequence": 252,
      "allow_embedding": "",
      "rating": 0,
      "rated_by": "0",
      "voter_ids": "",
      "featured": "no",
      "featured_order": null,
      "featured_date": "0000-00-00 00:00:00",
      "featured_description": "",
      "allow_rating": "yes",
      "allow_comments": "yes",
      "comments_count": 0,
      "last_commented": null,
      "active": "yes",
      "favourite_count": "0",
      "playlist_count": "0",
      "views": 0,
      "last_viewed": "0000-00-00 00:00:00",
      "date_added": "2023-03-29",
      "flagged": "no",
      "duration": " 0s",
      "status": "Successful",
      "failed_reason": "none",
      "default_thumb": 207443,
      "aspect_ratio": "",
      "embed_code": "",
      "refer_url": "",
      "downloads": 0,
      "uploader_ip": "110.93.192.18",
      "mass_embed_status": "no",
      "unique_embed_code": "",
      "remote_play_url": "",
      "video_files": "",
      "server_ip": "",
      "file_server_path": "",
      "file_directory": "2023/03/29",
      "files_thumbs_path": "",
      "file_thumbs_count": "",
      "has_hq": "no",
      "filegrp_size": "",
      "process_status": 0,
      "video_version": "2.7",
      "extras": "",
      "subscription_email": "pending",
      "thumbs_version": "3.0",
      "re_conv_status": "",
      "conv_progress": "",
      "is_premium": "no",
      "override_default_monetization": 0,
      "credits_required": null,
      "rental_hours": 0,
      "premium_cid": 0,
      "in_editor_pick": "no",
      "has_subs": "no",
      "total_subs": 0,
      "last_sub_num": 0,
      "live": "https://tes.ottervideo.ca/Outdoor/video.m3u8",
      "udp_live": "",
      "force_hls_http_url": "https://tes.ottervideo.ca/Outdoor/video.m3u8",
      "start_published_date": "2023-03-29 10:29:04",
      "end_published_date": null,
      "has_sprite": "no",
      "version": 1,
      "has_resulotion": "no",
      "aws_service_id": 0,
      "aws_cdn": "",
      "aws_thumb_path": "",
      "license_by": "",
      "is_channeHome": "no",
      "super_feature": 0,
      "is_avod": 1,
      "is_tvod": 0,
      "pre_order": 0,
      "live_status": 0,
      "deleted_at": null,
      "content_type": 4,
      "is_360": 0,
      "projection_type": "NONE",
      "epg_channel_id": "",
      "drm_protected": "no",
      "epg_url": "",
      "content_language": null,
      "dvr_url": "",
      "dvr_backup_timezone": "",
      "dvr_backup_duration": "0",
      "epg_dvr_catchup_url": "",
      "mpaa_rating": null,
      "content_rating_tags": null,
      "logo": "https://vcz-tesvideo-cloud-vodlix-com.b-cdn.net/u/tesvideo/files/video_logos/2023/03/29/1680054756waqEmr1AFw.png",
      "portrait_thumbs": {
        "original": "https://vcz-tesvideo-cloud-vodlix-com.b-cdn.net/u/tesvideo/files/thumbs/2023/03/29/1680054756waqEmr1AFw-original-portrait.jpg",
        "160x240": "https://vcz-tesvideo-cloud-vodlix-com.b-cdn.net/u/tesvideo/files/thumbs/2023/03/29/1680054756waqEmr1AFw-160x240-portrait.jpg",
        "240x360": "https://vcz-tesvideo-cloud-vodlix-com.b-cdn.net/u/tesvideo/files/thumbs/2023/03/29/1680054756waqEmr1AFw-240x360-portrait.jpg",
        "320x480": "https://vcz-tesvideo-cloud-vodlix-com.b-cdn.net/u/tesvideo/files/thumbs/2023/03/29/1680054756waqEmr1AFw-320x480-portrait.jpg",
        "480x720": "https://vcz-tesvideo-cloud-vodlix-com.b-cdn.net/u/tesvideo/files/thumbs/2023/03/29/1680054756waqEmr1AFw-480x720-portrait.jpg",
        "720x1080": "https://vcz-tesvideo-cloud-vodlix-com.b-cdn.net/u/tesvideo/files/thumbs/2023/03/29/1680054756waqEmr1AFw-720x1080-portrait.jpg"
      },
      "thumbs": {
        "original": "https://vcz-tesvideo-cloud-vodlix-com.b-cdn.net/u/tesvideo/files/thumbs/2023/03/29/1680054756waqEmr1AFw-original-KFo6h9FM.jpg",
        "168x105": "https://vcz-tesvideo-cloud-vodlix-com.b-cdn.net/u/tesvideo/files/thumbs/2023/03/29/1680054756waqEmr1AFw-168x105-KFo6h9FM.jpg",
        "416x260": "https://vcz-tesvideo-cloud-vodlix-com.b-cdn.net/u/tesvideo/files/thumbs/2023/03/29/1680054756waqEmr1AFw-416x260-KFo6h9FM.jpg",
        "632x395": "https://vcz-tesvideo-cloud-vodlix-com.b-cdn.net/u/tesvideo/files/thumbs/2023/03/29/1680054756waqEmr1AFw-632x395-KFo6h9FM.jpg",
        "768x432": "https://vcz-tesvideo-cloud-vodlix-com.b-cdn.net/u/tesvideo/files/thumbs/2023/03/29/1680054756waqEmr1AFw-768x432-KFo6h9FM.jpg",
        "1280x720": "https://vcz-tesvideo-cloud-vodlix-com.b-cdn.net/u/tesvideo/files/thumbs/2023/03/29/1680054756waqEmr1AFw-1280x720-KFo6h9FM.jpg",
        "1920x1080": "https://vcz-tesvideo-cloud-vodlix-com.b-cdn.net/u/tesvideo/files/thumbs/2023/03/29/1680054756waqEmr1AFw-1920x1080-KFo6h9FM.jpg",
        "200x288": "https://vcz-tesvideo-cloud-vodlix-com.b-cdn.net/u/tesvideo/files/thumbs/2023/03/29/1680054756waqEmr1AFw-200x288-KFo6h9FM.jpg"
      },
      "gif": null,
      "files": [
        "https://tes.ottervideo.ca/Outdoor/video.m3u8"
      ],
      "watch_url": "/watch/4479",
      "initials": "<?xml version=\"1.0\" encoding=\"utf-8\"?><svg width=\"48\" height=\"48\" xmlns=\"http://www.w3.org/2000/svg\" xmlns:xlink=\"http://www.w3.org/1999/xlink\"><circle cx=\"24\" cy=\"24\" r=\"24\" style=\"fill: none\" /><text x=\"50%\" y=\"50%\" dy=\".1em\" fill=\"#8b5d5d\" font-size=\"24\" text-anchor=\"middle\" dominant-baseline=\"middle\" style=\"font-family: OpenSans, sans-serif; line-height: 1\">OH</text></svg>",
      "year": "2023",
      "duration_in_seconds": "0",
      "rate": 0,
      "trailers": null,
      "fav_id": null,
      "is_fav": null,
      "url": "/watch/4479",
      "shareable": "https://trutv.transworld-home.com/watch/4479",
      "copy_url": "https://tesvideo.cloud.vodlix.com/movies/title/4479",
      "categories": [
        {
          "category_id": 6,
          "parent_id": 0,
          "category_name": "Documentary",
          "category_order": 46,
          "category_desc": "Documentary",
          "date_added": "2022-11-07 05:21:19",
          "category_thumb": "",
          "featured": "no",
          "isdefault": "no",
          "navbar": "no",
          "is_trailer": 0,
          "meta_title": null,
          "meta_description": null,
          "meta_keywords": "Documentary",
          "is_video": 0,
          "is_series": 0,
          "is_live": 1
        }
      ],
      "channel_number": 252,
      "max_resolution": "1080p",
      "square_thumbs": {
        "original": "https://vcz-tesvideo-cloud-vodlix-com.b-cdn.net/u/tesvideo/files/thumbs/2023/03/29/1680054756waqEmr1AFw-original-square.jpg",
        "300x300": "https://vcz-tesvideo-cloud-vodlix-com.b-cdn.net/u/tesvideo/files/thumbs/2023/03/29/1680054756waqEmr1AFw-300x300-square.jpg",
        "512x512": "https://vcz-tesvideo-cloud-vodlix-com.b-cdn.net/u/tesvideo/files/thumbs/2023/03/29/1680054756waqEmr1AFw-512x512-square.jpg",
        "1024x1024": "https://vcz-tesvideo-cloud-vodlix-com.b-cdn.net/u/tesvideo/files/thumbs/2023/03/29/1680054756waqEmr1AFw-1024x1024-square.jpg"
      },
      "interval": " 0s",
      "price_tag": null,
      "show_premium_badge": false,
      "can_pre_order": false,
      "availability_date": null,
      "content_type_label": "live"
    },
    {
      "videoid": 4478,
      "videokey": "YANMKNW81OBH",
      "video_password": null,
      "video_users": "",
      "username": "",
      "userid": 1,
      "partner_id": null,
      "maturity_level": "all",
      "title": "Nat Geo HD",
      "file_name": "1680054107WEa3bIAb4u",
      "file_type": 2,
      "description": "Nat Geo HD",
      "tags": "nat geo hd,documentary",
      "category": "#6# ",
      "category_parents": "",
      "broadcast": "public",
      "location": "0",
      "datecreated": "2023-03-29",
      "country": "0",
      "blocked_countries": "#0# ",
      "allowed_countries": "0",
      "sprite_count": 0,
      "season_id": 0,
      "series_id": 0,
      "sequence": 251,
      "allow_embedding": "",
      "rating": 0,
      "rated_by": "0",
      "voter_ids": "",
      "featured": "no",
      "featured_order": null,
      "featured_date": "0000-00-00 00:00:00",
      "featured_description": "",
      "allow_rating": "yes",
      "allow_comments": "yes",
      "comments_count": 0,
      "last_commented": null,
      "active": "yes",
      "favourite_count": "0",
      "playlist_count": "0",
      "views": 1,
      "last_viewed": "0000-00-00 00:00:00",
      "date_added": "2023-03-29",
      "flagged": "no",
      "duration": " 0s",
      "status": "Successful",
      "failed_reason": "none",
      "default_thumb": 207424,
      "aspect_ratio": "",
      "embed_code": "",
      "refer_url": "",
      "downloads": 0,
      "uploader_ip": "110.93.192.18",
      "mass_embed_status": "no",
      "unique_embed_code": "",
      "remote_play_url": "",
      "video_files": "",
      "server_ip": "",
      "file_server_path": "",
      "file_directory": "2023/03/29",
      "files_thumbs_path": "",
      "file_thumbs_count": "",
      "has_hq": "no",
      "filegrp_size": "",
      "process_status": 0,
      "video_version": "2.7",
      "extras": "",
      "subscription_email": "pending",
      "thumbs_version": "3.0",
      "re_conv_status": "",
      "conv_progress": "",
      "is_premium": "no",
      "override_default_monetization": 0,
      "credits_required": null,
      "rental_hours": 0,
      "premium_cid": 0,
      "in_editor_pick": "no",
      "has_subs": "no",
      "total_subs": 0,
      "last_sub_num": 0,
      "live": "https://tes.ottervideo.ca/Nat-Geo-HD/video.m3u8",
      "udp_live": "",
      "force_hls_http_url": "https://tes.ottervideo.ca/Nat-Geo-HD/video.m3u8",
      "start_published_date": "2023-03-29 10:26:20",
      "end_published_date": null,
      "has_sprite": "no",
      "version": 1,
      "has_resulotion": "no",
      "aws_service_id": 0,
      "aws_cdn": "",
      "aws_thumb_path": "",
      "license_by": "",
      "is_channeHome": "no",
      "super_feature": 0,
      "is_avod": 1,
      "is_tvod": 0,
      "pre_order": 0,
      "live_status": 0,
      "deleted_at": null,
      "content_type": 4,
      "is_360": 0,
      "projection_type": "NONE",
      "epg_channel_id": "",
      "drm_protected": "no",
      "epg_url": "",
      "content_language": null,
      "dvr_url": "",
      "dvr_backup_timezone": "",
      "dvr_backup_duration": "0",
      "epg_dvr_catchup_url": "",
      "mpaa_rating": null,
      "content_rating_tags": null,
      "logo": "https://vcz-tesvideo-cloud-vodlix-com.b-cdn.net/u/tesvideo/files/video_logos/2023/03/29/1680054107WEa3bIAb4u.png",
      "portrait_thumbs": {
        "original": "https://vcz-tesvideo-cloud-vodlix-com.b-cdn.net/u/tesvideo/files/thumbs/2023/03/29/1680054107WEa3bIAb4u-original-portrait.jpg",
        "160x240": "https://vcz-tesvideo-cloud-vodlix-com.b-cdn.net/u/tesvideo/files/thumbs/2023/03/29/1680054107WEa3bIAb4u-160x240-portrait.jpg",
        "240x360": "https://vcz-tesvideo-cloud-vodlix-com.b-cdn.net/u/tesvideo/files/thumbs/2023/03/29/1680054107WEa3bIAb4u-240x360-portrait.jpg",
        "320x480": "https://vcz-tesvideo-cloud-vodlix-com.b-cdn.net/u/tesvideo/files/thumbs/2023/03/29/1680054107WEa3bIAb4u-320x480-portrait.jpg",
        "480x720": "https://vcz-tesvideo-cloud-vodlix-com.b-cdn.net/u/tesvideo/files/thumbs/2023/03/29/1680054107WEa3bIAb4u-480x720-portrait.jpg",
        "720x1080": "https://vcz-tesvideo-cloud-vodlix-com.b-cdn.net/u/tesvideo/files/thumbs/2023/03/29/1680054107WEa3bIAb4u-720x1080-portrait.jpg"
      },
      "thumbs": {
        "original": "https://vcz-tesvideo-cloud-vodlix-com.b-cdn.net/u/tesvideo/files/thumbs/2023/03/29/1680054107WEa3bIAb4u-original-HVeZXLSp.jpg",
        "168x105": "https://vcz-tesvideo-cloud-vodlix-com.b-cdn.net/u/tesvideo/files/thumbs/2023/03/29/1680054107WEa3bIAb4u-168x105-HVeZXLSp.jpg",
        "416x260": "https://vcz-tesvideo-cloud-vodlix-com.b-cdn.net/u/tesvideo/files/thumbs/2023/03/29/1680054107WEa3bIAb4u-416x260-HVeZXLSp.jpg",
        "632x395": "https://vcz-tesvideo-cloud-vodlix-com.b-cdn.net/u/tesvideo/files/thumbs/2023/03/29/1680054107WEa3bIAb4u-632x395-HVeZXLSp.jpg",
        "768x432": "https://vcz-tesvideo-cloud-vodlix-com.b-cdn.net/u/tesvideo/files/thumbs/2023/03/29/1680054107WEa3bIAb4u-768x432-HVeZXLSp.jpg",
        "1280x720": "https://vcz-tesvideo-cloud-vodlix-com.b-cdn.net/u/tesvideo/files/thumbs/2023/03/29/1680054107WEa3bIAb4u-1280x720-HVeZXLSp.jpg",
        "1920x1080": "https://vcz-tesvideo-cloud-vodlix-com.b-cdn.net/u/tesvideo/files/thumbs/2023/03/29/1680054107WEa3bIAb4u-1920x1080-HVeZXLSp.jpg",
        "200x288": "https://vcz-tesvideo-cloud-vodlix-com.b-cdn.net/u/tesvideo/files/thumbs/2023/03/29/1680054107WEa3bIAb4u-200x288-HVeZXLSp.jpg"
      },
      "gif": null,
      "files": [
        "https://tes.ottervideo.ca/Nat-Geo-HD/video.m3u8"
      ],
      "watch_url": "/watch/4478",
      "initials": "<?xml version=\"1.0\" encoding=\"utf-8\"?><svg width=\"48\" height=\"48\" xmlns=\"http://www.w3.org/2000/svg\" xmlns:xlink=\"http://www.w3.org/1999/xlink\"><circle cx=\"24\" cy=\"24\" r=\"24\" style=\"fill: none\" /><text x=\"50%\" y=\"50%\" dy=\".1em\" fill=\"#8b5d5d\" font-size=\"24\" text-anchor=\"middle\" dominant-baseline=\"middle\" style=\"font-family: OpenSans, sans-serif; line-height: 1\">NH</text></svg>",
      "year": "2023",
      "duration_in_seconds": "0",
      "rate": 0,
      "trailers": null,
      "fav_id": null,
      "is_fav": null,
      "url": "/watch/4478",
      "shareable": "https://trutv.transworld-home.com/watch/4478",
      "copy_url": "https://tesvideo.cloud.vodlix.com/movies/title/4478",
      "categories": [
        {
          "category_id": 6,
          "parent_id": 0,
          "category_name": "Documentary",
          "category_order": 46,
          "category_desc": "Documentary",
          "date_added": "2022-11-07 05:21:19",
          "category_thumb": "",
          "featured": "no",
          "isdefault": "no",
          "navbar": "no",
          "is_trailer": 0,
          "meta_title": null,
          "meta_description": null,
          "meta_keywords": "Documentary",
          "is_video": 0,
          "is_series": 0,
          "is_live": 1
        }
      ],
      "channel_number": 251,
      "max_resolution": "1080p",
      "square_thumbs": {
        "original": "https://vcz-tesvideo-cloud-vodlix-com.b-cdn.net/u/tesvideo/files/thumbs/2023/03/29/1680054107WEa3bIAb4u-original-square.jpg",
        "300x300": "https://vcz-tesvideo-cloud-vodlix-com.b-cdn.net/u/tesvideo/files/thumbs/2023/03/29/1680054107WEa3bIAb4u-300x300-square.jpg",
        "512x512": "https://vcz-tesvideo-cloud-vodlix-com.b-cdn.net/u/tesvideo/files/thumbs/2023/03/29/1680054107WEa3bIAb4u-512x512-square.jpg",
        "1024x1024": "https://vcz-tesvideo-cloud-vodlix-com.b-cdn.net/u/tesvideo/files/thumbs/2023/03/29/1680054107WEa3bIAb4u-1024x1024-square.jpg"
      },
      "interval": " 0s",
      "price_tag": null,
      "show_premium_badge": false,
      "can_pre_order": false,
      "availability_date": null,
      "content_type_label": "live"
    },
    {
      "videoid": 4477,
      "videokey": "4WMNMSX4M1BR",
      "video_password": null,
      "video_users": "",
      "username": "",
      "userid": 1,
      "partner_id": null,
      "maturity_level": "all",
      "title": "Nick - ARY",
      "file_name": "1680034354FxksqWXFPE",
      "file_type": 2,
      "description": "Nick - ARY  Kids Channel",
      "tags": "nick hd - ary,kids",
      "category": "#55# ",
      "category_parents": "",
      "broadcast": "public",
      "location": "0",
      "datecreated": "2023-03-29",
      "country": "0",
      "blocked_countries": "",
      "allowed_countries": "0",
      "sprite_count": 0,
      "season_id": 0,
      "series_id": 0,
      "sequence": 242,
      "allow_embedding": "",
      "rating": 0,
      "rated_by": "0",
      "voter_ids": "",
      "featured": "no",
      "featured_order": null,
      "featured_date": "0000-00-00 00:00:00",
      "featured_description": "",
      "allow_rating": "yes",
      "allow_comments": "yes",
      "comments_count": 0,
      "last_commented": null,
      "active": "yes",
      "favourite_count": "0",
      "playlist_count": "0",
      "views": 0,
      "last_viewed": "0000-00-00 00:00:00",
      "date_added": "2023-03-29",
      "flagged": "no",
      "duration": " 0s",
      "status": "Successful",
      "failed_reason": "none",
      "default_thumb": 207668,
      "aspect_ratio": "",
      "embed_code": "",
      "refer_url": "",
      "downloads": 0,
      "uploader_ip": "110.93.192.18",
      "mass_embed_status": "no",
      "unique_embed_code": "",
      "remote_play_url": "",
      "video_files": "",
      "server_ip": "",
      "file_server_path": "",
      "file_directory": "2023/03/29",
      "files_thumbs_path": "",
      "file_thumbs_count": "",
      "has_hq": "no",
      "filegrp_size": "",
      "process_status": 0,
      "video_version": "2.7",
      "extras": "",
      "subscription_email": "pending",
      "thumbs_version": "3.0",
      "re_conv_status": "",
      "conv_progress": "",
      "is_premium": "no",
      "override_default_monetization": 0,
      "credits_required": null,
      "rental_hours": 0,
      "premium_cid": 0,
      "in_editor_pick": "no",
      "has_subs": "no",
      "total_subs": 0,
      "last_sub_num": 0,
      "live": "https://tes.ottervideo.ca/ARY-NICK/video.m3u8",
      "udp_live": "",
      "force_hls_http_url": "https://tes.ottervideo.ca/ARY-NICK/video.m3u8",
      "start_published_date": "2023-03-30 11:29:56",
      "end_published_date": null,
      "has_sprite": "no",
      "version": 1,
      "has_resulotion": "no",
      "aws_service_id": 0,
      "aws_cdn": "",
      "aws_thumb_path": "",
      "license_by": "",
      "is_channeHome": "no",
      "super_feature": 0,
      "is_avod": 1,
      "is_tvod": 0,
      "pre_order": 0,
      "live_status": 0,
      "deleted_at": null,
      "content_type": 4,
      "is_360": 0,
      "projection_type": "NONE",
      "epg_channel_id": "",
      "drm_protected": "no",
      "epg_url": "",
      "content_language": null,
      "dvr_url": "",
      "dvr_backup_timezone": "",
      "dvr_backup_duration": "0",
      "epg_dvr_catchup_url": "",
      "mpaa_rating": null,
      "content_rating_tags": null,
      "logo": "https://vcz-tesvideo-cloud-vodlix-com.b-cdn.net/u/tesvideo/files/video_logos/2023/03/29/1680034354FxksqWXFPE.png?du=1680157779",
      "portrait_thumbs": {
        "original": "https://vcz-tesvideo-cloud-vodlix-com.b-cdn.net/u/tesvideo/files/thumbs/2023/03/29/1680034354FxksqWXFPE-original-portrait.jpg",
        "160x240": "https://vcz-tesvideo-cloud-vodlix-com.b-cdn.net/u/tesvideo/files/thumbs/2023/03/29/1680034354FxksqWXFPE-160x240-portrait.jpg",
        "240x360": "https://vcz-tesvideo-cloud-vodlix-com.b-cdn.net/u/tesvideo/files/thumbs/2023/03/29/1680034354FxksqWXFPE-240x360-portrait.jpg",
        "320x480": "https://vcz-tesvideo-cloud-vodlix-com.b-cdn.net/u/tesvideo/files/thumbs/2023/03/29/1680034354FxksqWXFPE-320x480-portrait.jpg",
        "480x720": "https://vcz-tesvideo-cloud-vodlix-com.b-cdn.net/u/tesvideo/files/thumbs/2023/03/29/1680034354FxksqWXFPE-480x720-portrait.jpg",
        "720x1080": "https://vcz-tesvideo-cloud-vodlix-com.b-cdn.net/u/tesvideo/files/thumbs/2023/03/29/1680034354FxksqWXFPE-720x1080-portrait.jpg"
      },
      "thumbs": {
        "original": "https://vcz-tesvideo-cloud-vodlix-com.b-cdn.net/u/tesvideo/files/thumbs/2023/03/29/1680034354FxksqWXFPE-original-co18UH70.jpg",
        "168x105": "https://vcz-tesvideo-cloud-vodlix-com.b-cdn.net/u/tesvideo/files/thumbs/2023/03/29/1680034354FxksqWXFPE-168x105-co18UH70.jpg",
        "416x260": "https://vcz-tesvideo-cloud-vodlix-com.b-cdn.net/u/tesvideo/files/thumbs/2023/03/29/1680034354FxksqWXFPE-416x260-co18UH70.jpg",
        "632x395": "https://vcz-tesvideo-cloud-vodlix-com.b-cdn.net/u/tesvideo/files/thumbs/2023/03/29/1680034354FxksqWXFPE-632x395-co18UH70.jpg",
        "768x432": "https://vcz-tesvideo-cloud-vodlix-com.b-cdn.net/u/tesvideo/files/thumbs/2023/03/29/1680034354FxksqWXFPE-768x432-co18UH70.jpg",
        "1280x720": "https://vcz-tesvideo-cloud-vodlix-com.b-cdn.net/u/tesvideo/files/thumbs/2023/03/29/1680034354FxksqWXFPE-1280x720-co18UH70.jpg",
        "1920x1080": "https://vcz-tesvideo-cloud-vodlix-com.b-cdn.net/u/tesvideo/files/thumbs/2023/03/29/1680034354FxksqWXFPE-1920x1080-co18UH70.jpg",
        "200x288": "https://vcz-tesvideo-cloud-vodlix-com.b-cdn.net/u/tesvideo/files/thumbs/2023/03/29/1680034354FxksqWXFPE-200x288-co18UH70.jpg"
      },
      "gif": null,
      "files": [
        "https://tes.ottervideo.ca/ARY-NICK/video.m3u8"
      ],
      "watch_url": "/watch/4477",
      "initials": "<?xml version=\"1.0\" encoding=\"utf-8\"?><svg width=\"48\" height=\"48\" xmlns=\"http://www.w3.org/2000/svg\" xmlns:xlink=\"http://www.w3.org/1999/xlink\"><circle cx=\"24\" cy=\"24\" r=\"24\" style=\"fill: none\" /><text x=\"50%\" y=\"50%\" dy=\".1em\" fill=\"#8b5d5d\" font-size=\"24\" text-anchor=\"middle\" dominant-baseline=\"middle\" style=\"font-family: OpenSans, sans-serif; line-height: 1\">NA</text></svg>",
      "year": "2023",
      "duration_in_seconds": "0",
      "rate": 0,
      "trailers": null,
      "fav_id": null,
      "is_fav": null,
      "url": "/watch/4477",
      "shareable": "https://trutv.transworld-home.com/watch/4477",
      "copy_url": "https://tesvideo.cloud.vodlix.com/movies/title/4477",
      "categories": [
        {
          "category_id": 55,
          "parent_id": 0,
          "category_name": "Kids",
          "category_order": 2,
          "category_desc": "Kids",
          "date_added": "2023-03-29 10:19:59",
          "category_thumb": "",
          "featured": "no",
          "isdefault": "no",
          "navbar": "no",
          "is_trailer": 0,
          "meta_title": "Kids",
          "meta_description": "Kids",
          "meta_keywords": "Kids",
          "is_video": 0,
          "is_series": 0,
          "is_live": 1
        }
      ],
      "channel_number": 242,
      "max_resolution": "1080p",
      "square_thumbs": {
        "original": "https://vcz-tesvideo-cloud-vodlix-com.b-cdn.net/u/tesvideo/files/thumbs/2023/03/29/1680034354FxksqWXFPE-original-square.jpg",
        "300x300": "https://vcz-tesvideo-cloud-vodlix-com.b-cdn.net/u/tesvideo/files/thumbs/2023/03/29/1680034354FxksqWXFPE-300x300-square.jpg",
        "512x512": "https://vcz-tesvideo-cloud-vodlix-com.b-cdn.net/u/tesvideo/files/thumbs/2023/03/29/1680034354FxksqWXFPE-512x512-square.jpg",
        "1024x1024": "https://vcz-tesvideo-cloud-vodlix-com.b-cdn.net/u/tesvideo/files/thumbs/2023/03/29/1680034354FxksqWXFPE-1024x1024-square.jpg"
      },
      "interval": " 0s",
      "price_tag": null,
      "show_premium_badge": false,
      "can_pre_order": false,
      "availability_date": null,
      "content_type_label": "live"
    }
  ],
  "time": "0.197 s"
}